CHANGES.rst
DESCRIPTION.rst
LICENSE
MANIFEST.in
README.md
setup.py
src/wai/test/_AbstractTest.py
src/wai/test/_AbstractTestMeta.py
src/wai/test/__init__.py
src/wai/test/_constants.py
src/wai/test/_functions.py
src/wai/test/decorators/_ExceptionTest.py
src/wai/test/decorators/_ExpectedFailure.py
src/wai/test/decorators/_RegressionTest.py
src/wai/test/decorators/_Skip.py
src/wai/test/decorators/_SubjectArgs.py
src/wai/test/decorators/_Test.py
src/wai/test/decorators/_WithSerialiser.py
src/wai/test/decorators/__init__.py
src/wai/test/serialisation/_BytesSerialiser.py
src/wai/test/serialisation/_RegressionSerialiser.py
src/wai/test/serialisation/_StringSerialiser.py
src/wai/test/serialisation/__init__.py
src/wai_test.egg-info/PKG-INFO
src/wai_test.egg-info/SOURCES.txt
src/wai_test.egg-info/dependency_links.txt
src/wai_test.egg-info/top_level.txt