Metadata-Version: 2.1
Name: wai-test
Version: 0.0.4
Summary: Python library for unit tests.
Home-page: https://github.com/waikato-datamining/wai-test
Author: Corey Sterling
Author-email: coreytsterling@gmail.com
License: MIT
Classifier: Development Status :: 4 - Beta
Classifier: License :: OSI Approved :: MIT License
Classifier: Topic :: Scientific/Engineering :: Mathematics
Classifier: Programming Language :: Python :: 3
License-File: LICENSE
